auto_remove_with_dependencies/__init__.py
auto_remove_with_dependencies/__main__.py
auto_remove_with_dependencies/constants.py
auto_remove_with_dependencies/core.py
auto_remove_with_dependencies-0.3.2.dist-info/licenses/LICENSE
auto_remove_with_dependencies-0.3.2.dist-info/METADATA
auto_remove_with_dependencies-0.3.2.dist-info/WHEEL
auto_remove_with_dependencies-0.3.2.dist-info/entry_points.txt
auto_remove_with_dependencies-0.3.2.dist-info/top_level.txt
auto_remove_with_dependencies-0.3.2.dist-info/RECORD
