Metadata-Version: 2.4
Name: auto_remove_with_dependencies
Version: 0.3.2
Summary: A pip auxiliar that uninstall the packages passed and its unused dependencies.
Home-page: https://github.com/mayronjr/pip-remove-with-dependencies
Author: Mayron Moura Soares Junior
Author-email: mayronjunior5@gmail.com
License: MIT
Classifier: Programming Language :: Python :: 3.9
Classifier: Programming Language :: Python :: 3.10
Classifier: Programming Language :: Python :: 3.11
Classifier: Programming Language :: Python :: 3.12
Classifier: Programming Language :: Python :: 3.13
Classifier: License :: OSI Approved :: MIT License
Classifier: Operating System :: OS Independent
Requires-Python: >=3.9
License-File: LICENSE
Requires-Dist: packaging>=20.0
Dynamic: author
Dynamic: author-email
Dynamic: classifier
Dynamic: description
Dynamic: description-content-type
Dynamic: home-page
Dynamic: license
Dynamic: license-file
Dynamic: requires-dist
Dynamic: requires-python
Dynamic: summary
